fabric_anaconda-0.0.7.dist-info/DESCRIPTION.rst
fabric_anaconda-0.0.7.dist-info/METADATA
fabric_anaconda-0.0.7.dist-info/RECORD
fabric_anaconda-0.0.7.dist-info/WHEEL
fabric_anaconda-0.0.7.dist-info/metadata.json
fabric_anaconda-0.0.7.dist-info/top_level.txt
fabriconda/__init__.py
