Metadata-Version: 2.0
Name: fabric-anaconda
Version: 0.0.7
Summary: Some additional functions for working with anaconda environments in Fabric.
Home-page: http://pypi.python.org/pypi/fabric-anaconda/
Author: Barnaby Gray
Author-email: barnaby@pickle.me.uk
License: UNKNOWN
Platform: UNKNOWN
Requires-Dist: Fabric
